Metadata-Version: 2.1
Name: arrayfiles
Version: 0.0.1
Summary: Array-like File Access in Python
Home-page: https://github.com/yasufumy/arrayfiles
Author: Yasufumi Taniguchi
Author-email: yasufumi.taniguchi@gmail.com
License: MIT
Platform: UNKNOWN
Classifier: Programming Language :: Python :: 3.6
Classifier: Programming Language :: Python :: 3.7
Classifier: Programming Language :: Python :: 3.8
